MLTask_utils/__init__.py
MLTask_utils/AI/__init__.py
MLTask_utils/AI/ElevenLabs/ElevenLabsManager.py
MLTask_utils/AI/ElevenLabs/__init__.py
MLTask_utils/AI/OpenAI/LocalWhisper.py
MLTask_utils/AI/OpenAI/OpenAIManager.py
MLTask_utils/AI/OpenAI/__init__.py
MLTask_utils/AI/StabilityAI/StabilityAIManager.py
MLTask_utils/AI/StabilityAI/__init__.py
MLTask_utils/AWS/DynamoDBManager.py
MLTask_utils/AWS/DynamoDBManagerUtils.py
MLTask_utils/AWS/GQLManager.py
MLTask_utils/AWS/S3Utils.py
MLTask_utils/AWS/SageMakerManager.py
MLTask_utils/AWS/__init__.py
MLTask_utils/MLTask/TaskUtils.py
MLTask_utils/MLTask/__init__.py
MLTask_utils/Social/__init__.py
MLTask_utils/Social/Facebook/FacebookAuthenticator.py
MLTask_utils/Social/Facebook/FacebookPagePoster.py
MLTask_utils/Social/Facebook/__init__.py
MLTask_utils/Social/Instagram/InstagramPoster.py
MLTask_utils/Social/Instagram/__init__.py
MLTask_utils/Social/Instagram/instaposter.py
MLTask_utils/Social/Tiktok/TiktokAuthenticator.py
MLTask_utils/Social/Tiktok/TiktokDownloader.py
MLTask_utils/Social/Tiktok/TiktokManager.py
MLTask_utils/Social/Tiktok/TiktokPoster.py
MLTask_utils/Social/Tiktok/__init__.py
MLTask_utils/Social/Twitch/TwitchBot.py
MLTask_utils/Social/Twitch/__init__.py
MLTask_utils/Social/Twitch/twitchmanager.py
MLTask_utils/Social/Twitter/TwitterAPIWrapper.py
MLTask_utils/Social/Twitter/TwitterAuthenticator.py
MLTask_utils/Social/Twitter/TwitterPoster.py
MLTask_utils/Social/Twitter/__init__.py
MLTask_utils/Social/Youtube/Img2Lookbook.py
MLTask_utils/Social/Youtube/YoutubeAuthenticator.py
MLTask_utils/Social/Youtube/YoutubeDownloaderTool.py
MLTask_utils/Social/Youtube/YoutubeLiveManager.py
MLTask_utils/Social/Youtube/YoutubeManager.py
MLTask_utils/Social/Youtube/YoutubePoster.py
MLTask_utils/Social/Youtube/__init__.py
MLTask_utils/Social/pinterest/__init__.py
MLTask_utils/Social/pinterest/pinterestmanager.py
MLTask_utils/Social/streamElements/SEWebsocket.py
MLTask_utils/Social/streamElements/__init__.py
MLTask_utils-0.0.2.dist-info/LICENSE
MLTask_utils-0.0.2.dist-info/METADATA
MLTask_utils-0.0.2.dist-info/WHEEL
MLTask_utils-0.0.2.dist-info/top_level.txt
MLTask_utils-0.0.2.dist-info/RECORD
